modules/grayscale/rgb565Grayscaleelse_opti.v
 module rgb565Grayscaleelse_opti #(parameter [7:0] customInstructionID = 8'd0)
                            (input wire         start,
                             input wire [31:0]  valueA,
                             input wire [31:0]  valueB,
                             input wire [7:0]   isId,
                             output wire        done,
                             output wire [31:0] result);

    wire isMe = (isId == customInstructionID) ? start : 1'b0;

    // Pixel0
    wire [7:0] red0 = {valueA[15:11], 3'b0};
    wire [7:0] green0 = {valueA[10: 5], 2'b0};
    wire [7:0] blue0 = {valueA[4:0], 3'b0};
    wire [15:0] grayscale_result0 = (red0*54+green0*183+blue0*19) >> 8;

    // Pixel1
    wire [7:0] red1 = {valueA[31:27], 3'b0};
    wire [7:0] green1 = {valueA[26: 21], 2'b0};
    wire [7:0] blue1 = {valueA[20:16], 3'b0};
    wire [15:0] grayscale_result1 = (red1*54+green1*183+blue1*19) >> 8;

    // Pixel2
    wire [7:0] red2 = {valueB[15:11], 3'b0};
    wire [7:0] green2 = {valueB[10: 5], 2'b0};
    wire [7:0] blue2 = {valueB[4:0], 3'b0};
    wire [15:0] grayscale_result2 = (red2*54+green2*183+blue2*19) >> 8;

    // Pixel3
    wire [7:0] red3 = {valueB[31:27], 3'b0};
    wire [7:0] green3 = {valueB[26: 21], 2'b0};
    wire [7:0] blue3 = {valueB[20:16], 3'b0};
    wire [15:0] grayscale_result3 = (red3*54+green3*183+blue3*19) >> 8;

    assign result = isMe ? {grayscale_result3[7:0], grayscale_result2[7:0], grayscale_result1[7:0], grayscale_result0[7:0]} : 32'b0;


    assign done = isMe ? start : 1'b0;


endmodule

/* 
In RGB565, red = 5'b11111 (max intensity)
If we don't shift, we keep 31 in decimal
In RGB888, red max intensity is 255, not 31 !

Shift (normalize) grayscale result as a pixel contains 8 bits per color channel (to express grayscale)
*/

modules/grayscale/rgb565Grayscaleelse_opti_tb.v
 
`timescale 1ns / 1ps

// This tb has not been update to opti but only served to verify the module doesn't have syntax errors

module rgb565Grayscaleelse_opti_tb;

  // Testbench signals
  reg start;
  reg [31:0] valueA;
  reg [7:0] iseld;
  wire done;
  wire [31:0] result;

  // Instantiate the DUT (Device Under Test)
  rgb565Grayscaleelse_opti #(
      .customInstructionID(8'd101)
  ) dut (
      .start (start),
      .valueA(valueA),
      .isId (iseld),
      .done  (done),
      .result(result)
  );

  // Testbench procedure
  initial begin
    // Initialize signals
    start  = 0;
    valueA = 32'h00000000;
    iseld  = 8'd0;

    // Apply test cases
    #10;
    start  = 1;
    valueA = 32'h00007C1F;  // RGB: (31, 0, 31) in RGB565
    iseld  = 8'd101;  // Matching customInstructionId
    #10;

    start = 0;
    #10;

    start  = 1;
    valueA = 32'h0000F800;  // RGB: (31, 0, 0) in RGB565
    iseld  = 8'd101;
    #10;

    start  = 1;
    valueA = 32'h000007E0;  // RGB: (0, 63, 0) in RGB565
    iseld  = 8'd101;
    #10;

    start  = 1;
    valueA = 32'h0000001F;  // RGB: (0, 0, 31) in RGB565
    iseld  = 8'd101;
    #10;

    start  = 1;
    valueA = 32'h0000FFFF;  // White (31, 63, 31) in RGB565
    iseld  = 8'd101;
    #10;

    start  = 1;
    valueA = 32'h00000000;  // Black (0, 0, 0)
    iseld  = 8'd101;
    #10;

    // Test with different iseld (should not activate)
    start  = 1;
    valueA = 32'h00007C1F;
    iseld  = 8'd100;  // Different from customInstructionId
    #10;

    $finish;
  end
  initial begin
    $dumpfile("grayScaler.vcd");
    $dumpvars(1, dut);
  end

endmodule

modules/grayscale/grayScaler.vcd
$date
	Wed Mar 19 12:36:59 2025
$end
$version
	Icarus Verilog
$end
$timescale
	1ps
$end
$scope module rgb565Grayscaleelse_opti_tb $end
$scope module dut $end
$var wire 8 ! isId [7:0] $end
$var wire 1 " start $end
$var wire 32 # valueA [31:0] $end
$var wire 32 $ valueB [31:0] $end
$var wire 32 % result [31:0] $end
$var wire 8 & red3 [7:0] $end
$var wire 8 ' red2 [7:0] $end
$var wire 8 ( red1 [7:0] $end
$var wire 8 ) red0 [7:0] $end
$var wire 1 * isMe $end
$var wire 8 + green3 [7:0] $end
$var wire 8 , green2 [7:0] $end
$var wire 8 - green1 [7:0] $end
$var wire 8 . green0 [7:0] $end
$var wire 16 / grayscale_result3 [15:0] $end
$var wire 16 0 grayscale_result2 [15:0] $end
$var wire 16 1 grayscale_result1 [15:0] $end
$var wire 16 2 grayscale_result0 [15:0] $end
$var wire 1 3 done $end
$var wire 8 4 blue3 [7:0] $end
$var wire 8 5 blue2 [7:0] $end
$var wire 8 6 blue1 [7:0] $end
$var wire 8 7 blue0 [7:0] $end
$var parameter 8 8 customInstructionID $end
$upscope $end
$upscope $end
$enddefinitions $end
$comment Show the parameter values. $end
$dumpall
b1100101 8
$end
#0
$dumpvars
b0 7
b0 6
bz000 5
bz000 4
03
b0 2
b0 1
bx 0
bx /
b0 .
b0 -
bz00 ,
bz00 +
0*
b0 )
b0 (
bz000 '
bz000 &
b0 %
bz $
b0 #
0"
b0 !
$end
#10000
b10000111 2
bx0000000010000111 %
13
b1111000 )
b10000000 .
b11111000 7
1*
b1100101 !
b111110000011111 #
1"
#20000
b0 %
0*
03
0"
#30000
b110100 2
b11111000 )
b0 .
b0 7
bx0000000000110100 %
13
1*
b1111100000000000 #
1"
#40000
bx0000000010110100 %
b10110100 2
b0 )
b11111100 .
b11111100000 #
#50000
bx0000000000010010 %
b10010 2
b0 .
b11111000 7
b11111 #
#60000
bx0000000011111010 %
b11111010 2
b11111000 )
b11111100 .
b1111111111111111 #
#70000
bx0000000000000000 %
b0 2
b0 )
b0 .
b0 7
b0 #
#80000
b10000111 2
b0 %
03
b1111000 )
b10000000 .
b11111000 7
0*
b1100100 !
b111110000011111 #
