modules/grayscale/rgb565Grayscaleelse.v
module rgb565Grayscaleelse #(parameter [7:0] customInstructionID = 8'd0)
                            (input wire         start,
                             input wire [31:0]  valueA,
                             input wire [7:0]   isId,
                             output wire        done,
                             output wire [31:0] result);

    wire isMe = (isId == customInstructionID) ? start : 1'b0;

    wire [7:0] red = {valueA[15:11], 3'b0};
    wire [7:0] green = {valueA[10: 5], 2'b0};
    wire [7:0] blue = {valueA[4:0], 3'b0};
    wire [15:0] grayscale_result = (red*54+green*183+blue*19) >> 8;

    assign done = isMe ? start : 1'b0;
    assign result = isMe ? {24'b0, grayscale_result[7:0]} : 32'b0;


endmodule

/* 
In RGB565, red = 5'b11111 (max intensity)
If we don't shift, we keep 31 in decimal
In RGB888, red max intensity is 255, not 31 !

Shift (normalize) grayscale result as a pixel contains 8 bits per color channel (to express grayscale)
*/

modules/grayscale/rgb565Grayscaleelse_tb.v
 
`timescale 1ns / 1ps

module rgb565Grayscaleelse_tb;

  // Testbench signals
  reg start;
  reg [31:0] valueA;
  reg [7:0] iseld;
  wire done;
  wire [31:0] result;

  // Instantiate the DUT (Device Under Test)
  rgb565Grayscaleelse #(
      .customInstructionID(8'd101)
  ) dut (
      .start (start),
      .valueA(valueA),
      .isId (iseld),
      .done  (done),
      .result(result)
  );

  // Testbench procedure
  initial begin
    // Initialize signals
    start  = 0;
    valueA = 32'h00000000;
    iseld  = 8'd0;

    // Apply test cases
    #10;
    start  = 1;
    valueA = 32'h00007C1F;  // RGB: (31, 0, 31) in RGB565
    iseld  = 8'd101;  // Matching customInstructionId
    #10;

    start = 0;
    #10;

    start  = 1;
    valueA = 32'h0000F800;  // RGB: (31, 0, 0) in RGB565
    iseld  = 8'd101;
    #10;

    start  = 1;
    valueA = 32'h000007E0;  // RGB: (0, 63, 0) in RGB565
    iseld  = 8'd101;
    #10;

    start  = 1;
    valueA = 32'h0000001F;  // RGB: (0, 0, 31) in RGB565
    iseld  = 8'd101;
    #10;

    start  = 1;
    valueA = 32'h0000FFFF;  // White (31, 63, 31) in RGB565
    iseld  = 8'd101;
    #10;

    start  = 1;
    valueA = 32'h00000000;  // Black (0, 0, 0)
    iseld  = 8'd101;
    #10;

    // Test with different iseld (should not activate)
    start  = 1;
    valueA = 32'h00007C1F;
    iseld  = 8'd100;  // Different from customInstructionId
    #10;

    $finish;
  end
  initial begin
    $dumpfile("grayScaler.vcd");
    $dumpvars(1, dut);
  end

endmodule

modules/grayscale/grayScaler.vcd
$date
	Wed Mar 19 09:25:17 2025
$end
$version
	Icarus Verilog
$end
$timescale
	1ps
$end
$scope module rgb565Grayscaleelse_tb $end
$scope module dut $end
$var wire 8 ! isId [7:0] $end
$var wire 1 " start $end
$var wire 32 # valueA [31:0] $end
$var wire 32 $ result [31:0] $end
$var wire 8 % red [7:0] $end
$var wire 1 & isMe $end
$var wire 8 ' green [7:0] $end
$var wire 16 ( grayscale_result [15:0] $end
$var wire 1 ) done $end
$var wire 8 * blue [7:0] $end
$var parameter 8 + customInstructionID $end
$upscope $end
$upscope $end
$enddefinitions $end
$comment Show the parameter values. $end
$dumpall
b1100101 +
$end
#0
$dumpvars
b0 *
0)
b0 (
b0 '
0&
b0 %
b0 $
b0 #
0"
b0 !
$end
#10000
b10000111 $
b10000111 (
1)
b1111000 %
b10000000 '
b11111000 *
1&
b1100101 !
b111110000011111 #
1"
#20000
b0 $
0&
0)
0"
#30000
b110100 (
b11111000 %
b0 '
b0 *
1)
b110100 $
1&
b1111100000000000 #
1"
#40000
b10110100 $
b10110100 (
b0 %
b11111100 '
b11111100000 #
#50000
b10010 $
b10010 (
b0 '
b11111000 *
b11111 #
#60000
b11111010 $
b11111010 (
b11111000 %
b11111100 '
b1111111111111111 #
#70000
b0 $
b0 (
b0 %
b0 '
b0 *
b0 #
#80000
b10000111 (
0)
b1111000 %
b10000000 '
b11111000 *
0&
b1100100 !
b111110000011111 #
