modules/profiling/profileCi.v
module profileCi #( parameter [7:0] customId = 8'h00 )
                  ( input wire        start,
                                      clock,
                                      reset,
                                      stall,
                                      busIdle,
                    input wire [31:0] valueA,
                                      valueB,
                    input wire [7:0]  ciN,
                    output wire       done,
                    output reg [31:0] result );


    // 32-bit counters
    reg[31:0] counter0, counter1, counter2, counter3;

    // done signal
    assign done = (ciN == customId) && start;

    always @(posedge clock or posedge reset) begin
      if (reset) begin
        // Initialize counters to 0
        counter0 <= 32'b0;
        counter1 <= 32'b0;
        counter2 <= 32'b0;
        counter3 <= 32'b0;

        end
        else begin
            // valueB to control counters
            if (valueB[8]) counter0 <= 32'b0; // Reset counter0
            else if (valueB[4]) counter0 <= counter0; // Disable counter0 (remains unchanged)
            else if (valueB[0]) counter0 <= counter0 + 1; // Enable counter0

            if (valueB[9]) counter1 <= 32'b0; // Reset counter1
            else if (valueB[5]) counter1 <= counter1; // Disable counter1 (remains unchanged)
            else if (valueB[1] && stall) counter1 <= counter1 + 1; // Enable counter1 (µC stall cycles)

            if (valueB[10]) counter2 <= 32'b0; // Reset counter2
            else if (valueB[6]) counter2 <= counter2; // Disable counter2 (remains unchanged)
            else if (valueB[2] && busIdle) counter2 <= counter2 + 1; // Enable counter2 (bus-idle cycles)

            if (valueB[11]) counter3 <= 32'b0; // Reset counter3
            else if (valueB[7]) counter3 <= counter3; // Disable counter3 (remains unchanged)
            else if (valueB[3]) counter3 <= counter3 + 1; // Enable counter3
        end
    end

    // valueA to control output
    always @(*) begin
        if (!done)
            result <= 32'b0;
        else
            case (valueA[1:0])
                2'd0 : result <= counter0;
                2'd1 : result <= counter1;
                2'd2 : result <= counter2;
                2'd3 : result <= counter3;
                default : result <= 32'b0; // Recall RTL course
            endcase
    end

endmodule

modules/profiling/profileCi_tb.v
`timescale 1ps/1ps

module profileCi_tb;

 reg reset, clock;
  initial 
    begin
      reset = 1'b1;
      clock = 1'b0;                 
      repeat (4) #5 clock = ~clock; 
      reset = 1'b0;                 
      forever #5 clock = ~clock;
    end

reg s_start, s_stall, s_busIdle;
reg [31:0 ]s_valueA, s_valueB;
reg [7:0] s_ciN;
wire s_done;
wire [31:0] s_result;

profileCi #(.customId(8'd8)) DUT
	(.start(s_start),
	.clock(clock),
	.reset(reset),
	.stall(s_stall),
	.busIdle(s_busIdle),
	.valueA(s_valueA),
	.valueB(s_valueB),
	.ciN(s_ciN),
	.done(s_done),
	.result(s_result));

initial
  begin
    s_ciN = 8'h11; // wrong id, output should remain 0
    s_valueA[1:0] = 2'd0; //select counter0 output
    s_valueB[11:0] = 12'b000011100001; // enables counter 0, disable others
    s_start = 1'b1;

    @(negedge reset);            // wait for the reset period to end
    repeat(10) @(negedge clock);  // wait
    
    s_ciN = 8'd8; // right id, profileCi should activate - counter0 should count
    repeat(10) @(negedge clock);  // wait for 10 clock cycles

    s_ciN = 8'h11;// to check if output is forced back to 0 when ciN!=customId
    s_valueB[11:0] = 12'b111111111111;
    repeat(2) @(negedge clock);

    s_ciN = 8'd8;
    s_valueA[1:0] = 2'd1; //select counter1 output
    s_valueB[11:0] = 12'b000011000011; // enables counter 0 / 1, disable others
    s_stall = 1'b1; // counter 1 activates with stall raised
    repeat(5) @(negedge clock);

    s_valueA[1:0] = 2'd00012; //select counter2 output
    s_valueB[11:0] = 12'b000110000111; // enables counter 0 / 1 / 2, disable 4, reset 0
    s_busIdle = 1'b1; // counter 2 activates with busIdle raised
    repeat(5) @(negedge clock);
    // counter0 will remain zero because it's constantly reset

    $finish;	// decomment when using iVerilog
  end


// decomment when using iVerilog
 initial
    begin
      $dumpfile("profileCi_waves.vcd"); /* define the name of the .vcd file that can be viewed by GTKWAVE */
      $dumpvars(1,DUT);             /* dump all signals inside the DUT-component in the .vcd file */
    end


endmodule

modules/profiling/profileCi_waves.vcd
$date
	Mon Mar 17 18:08:18 2025
$end
$version
	Icarus Verilog
$end
$timescale
	1ps
$end
$scope module profileCi_tb $end
$scope module DUT $end
$var wire 1 ! busIdle $end
$var wire 8 " ciN [7:0] $end
$var wire 1 # clock $end
$var wire 1 $ done $end
$var wire 1 % reset $end
$var wire 1 & stall $end
$var wire 1 ' start $end
$var wire 32 ( valueA [31:0] $end
$var wire 32 ) valueB [31:0] $end
$var parameter 8 * customId $end
$var reg 32 + counter0 [31:0] $end
$var reg 32 , counter1 [31:0] $end
$var reg 32 - counter2 [31:0] $end
$var reg 32 . counter3 [31:0] $end
$var reg 32 / result [31:0] $end
$upscope $end
$upscope $end
$enddefinitions $end
$comment Show the parameter values. $end
$dumpall
b1000 *
$end
#0
$dumpvars
b0 /
b0 .
b0 -
b0 ,
b0 +
bx000011100001 )
bx00 (
1'
x&
1%
0$
0#
b10001 "
x!
$end
#5
1#
#10
0#
#15
1#
#20
0%
0#
#25
b1 +
1#
#30
0#
#35
b10 +
1#
#40
0#
#45
b11 +
1#
#50
0#
#55
b100 +
1#
#60
0#
#65
b101 +
1#
#70
0#
#75
b110 +
1#
#80
0#
#85
b111 +
1#
#90
0#
#95
b1000 +
1#
#100
0#
#105
b1001 +
1#
#110
0#
#115
b1010 +
1#
#120
b1010 /
1$
b1000 "
0#
#125
b1011 /
b1011 +
1#
#130
0#
#135
b1100 /
b1100 +
1#
#140
0#
#145
b1101 /
b1101 +
1#
#150
0#
#155
b1110 /
b1110 +
1#
#160
0#
#165
b1111 /
b1111 +
1#
#170
0#
#175
b10000 /
b10000 +
1#
#180
0#
#185
b10001 /
b10001 +
1#
#190
0#
#195
b10010 /
b10010 +
1#
#200
0#
#205
b10011 /
b10011 +
1#
#210
0#
#215
b10100 /
b10100 +
1#
#220
b0 /
0$
bx111111111111 )
b10001 "
0#
#225
b0 +
1#
#230
0#
#235
1#
#240
1$
1&
bx000011000011 )
bx01 (
b1000 "
0#
#245
b1 /
b1 ,
b1 +
1#
#250
0#
#255
b10 /
b10 ,
b10 +
1#
#260
0#
#265
b11 /
b11 ,
b11 +
1#
#270
0#
#275
b100 /
b100 ,
b100 +
1#
#280
0#
#285
b101 /
b101 ,
b101 +
1#
#290
b0 /
1!
bx000110000111 )
bx10 (
0#
#295
b1 /
b1 -
b110 ,
b0 +
1#
#300
0#
#305
b10 /
b10 -
b111 ,
1#
#310
0#
#315
b11 /
b11 -
b1000 ,
1#
#320
0#
#325
b100 /
b100 -
b1001 ,
1#
#330
0#
#335
b101 /
b101 -
b1010 ,
1#
