modules/profiling/counter.v
module counter #( parameter WIDTH = 32)
                ( input wire reset,
                             clock,
                             enable,
                             direction, /* a 1 is counting up, a 0 is counting down */
                  output reg [WIDTH-1:0] counterValue);

  always @(posedge clock)
    counterValue <= (reset == 1'b1) ? {WIDTH{1'b0}} : 
                    (enable == 1'b0) ? counterValue :
                    (direction == 1'b1) ? counterValue + 1 : counterValue - 1;
endmodule

modules/profiling/profileCi.v
module profileCi #( parameter [7:0] customId = 8'h00 )
                  ( input wire        start,
                                      clock,
                                      reset,
                                      stall,
                                      busIdle,
                    input wire [31:0] valueA,
                                      valueB,
                    input wire [7:0]  ciN,
                    output reg       done,
                    output reg [31:0] result );

    wire[31:0] counter0_value, counter1_value, counter2_value, counter3_value;
    reg counter0_reset, counter1_reset, counter2_reset, counter3_reset;
    reg counter0_enable, counter1_enable, counter2_enable, counter3_enable;

    wire isMe = (ciN == customId) ? start : 1'b0;
    reg [31:0] profile_result;

  always @(posedge clock or posedge reset) begin
    if (reset) begin

      done <= 1'b0;
      result <= 32'h00000000;
      counter0_enable <= 1'b0;
      counter1_enable <= 1'b0;
      counter2_enable <= 1'b0;
      counter3_enable <= 1'b0;

      counter0_reset <= 1'b0;
      counter1_reset <= 1'b0;
      counter2_reset <= 1'b0;
      counter3_reset <= 1'b0;

    end else begin
      if (isMe) begin
        done <= 1'b1;
        result <= profile_result;
      end else begin
        done   <= 1'b0;
        result <= 32'h00000000;
      end
      counter0_enable <= ((reset) || (valueB[4] && isMe))? 1'b0 : ((valueB[0]&& isMe) ? 1'b1 : counter0_enable);
      counter1_enable <= ((reset) || (valueB[5] && isMe))? 1'b0 : ((valueB[1]&& isMe) ? 1'b1 : counter1_enable);
      counter2_enable <= ((reset) || (valueB[6] && isMe))? 1'b0 : ((valueB[2]&& isMe) ? 1'b1 : counter2_enable);
      counter3_enable <= ((reset) || (valueB[7] && isMe))? 1'b0 : ((valueB[3]&& isMe) ? 1'b1 : counter3_enable);

      counter0_reset <= isMe ? valueB[8] : 1'b0;
      counter1_reset <= isMe ? valueB[9] : 1'b0;
      counter2_reset <= isMe ? valueB[10] : 1'b0;
      counter3_reset <= isMe ? valueB[11] : 1'b0;
    end
  end

  always @(*) begin
    case (valueA[1:0])
      2'b00:   profile_result = counter0_value;
      2'b01:   profile_result = counter1_value;
      2'b10:   profile_result = counter2_value;
      2'b11:   profile_result = counter3_value;
      default: profile_result = 32'h00000000;
    endcase
  end


  counter #(.WIDTH(32)) counter0 (.reset(counter0_reset), .clock(clock), .enable(counter0_enable), .direction(1'b1), .counterValue(counter0_value));
  counter #(.WIDTH(32)) counter1 (.reset(counter1_reset), .clock(clock), .enable(counter1_enable && stall), .direction(1'b1), .counterValue(counter1_value));
  counter #(.WIDTH(32)) counter2 (.reset(counter2_reset), .clock(clock), .enable(counter2_enable && busIdle), .direction(1'b1), .counterValue(counter2_value));
  counter #(.WIDTH(32)) counter3 (.reset(counter3_reset), .clock(clock), .enable(counter3_enable), .direction(1'b1), .counterValue(counter3_value));

endmodule

modules/profiling/profileCi_tb.v
`timescale 1ps/1ps

module profileCi_tb;

 reg reset, clock;
  initial 
    begin
      reset = 1'b1;
      clock = 1'b0;                 
      repeat (4) #5 clock = ~clock; 
      reset = 1'b0;                 
      forever #5 clock = ~clock;
    end

reg s_start, s_stall, s_busIdle;
reg [31:0 ]s_valueA, s_valueB;
reg [7:0] s_ciN;
wire s_done;
wire [31:0] s_result;

profileCi #(.customId(8'd8)) DUT
	(.start(s_start),
	.clock(clock),
	.reset(reset),
	.stall(s_stall),
	.busIdle(s_busIdle),
	.valueA(s_valueA),
	.valueB(s_valueB),
	.ciN(s_ciN),
	.done(s_done),
	.result(s_result));

initial
  begin
    s_ciN = 8'h11; // wrong id, output should remain 0
    s_valueA[1:0] = 4'b0000; //select counter0 output
    s_valueB[11:0] = 12'b000011100001; // enables counter 0, disable others
    s_start = 1'b1;

    @(negedge reset);            // wait for the reset period to end
    repeat(10) @(negedge clock);  // wait
    
    s_ciN = 8'd8; // right id, profileCi should activate - counter0 should count
    repeat(10) @(negedge clock);  // wait for 10 clock cycles

    s_ciN = 8'h11;// to check if output is forced back to 0 when ciN!=customId
    s_valueB[11:0] = 12'b111111111111;
    repeat(2) @(negedge clock);

    s_ciN = 8'd8;
    s_valueA[1:0] = 2'd1; //select counter1 output
    s_valueB[11:0] = 12'b000011000011; // enables counter 0 / 1, disable others
    s_stall = 1'b1; // counter 1 activates with stall raised
    repeat(5) @(negedge clock);

    s_valueA[1:0] = 2'd2; //select counter2 output
    s_valueB[11:0] = 12'b000110000111; // enables counter 0 / 1 / 2, disable 4, reset 0
    s_busIdle = 1'b1; // counter 2 activates with busIdle raised
    repeat(5) @(negedge clock);
    // counter0 will remain zero because it's constantly reset

    $finish;	// decomment when using iVerilog
  end


// decomment when using iVerilog
 initial
    begin
      $dumpfile("profileCi_waves.vcd"); /* define the name of the .vcd file that can be viewed by GTKWAVE */
      $dumpvars(1,DUT);             /* dump all signals inside the DUT-component in the .vcd file */
    end


endmodule

modules/profiling/profileCi_waves.vcd
$date
	Tue Mar 18 12:08:49 2025
$end
$version
	Icarus Verilog
$end
$timescale
	1ps
$end
$scope module profileCi_tb $end
$scope module DUT $end
$var wire 1 ! busIdle $end
$var wire 8 " ciN [7:0] $end
$var wire 1 # clock $end
$var wire 1 $ done $end
$var wire 1 % reset $end
$var wire 1 & stall $end
$var wire 1 ' start $end
$var wire 32 ( valueA [31:0] $end
$var wire 32 ) valueB [31:0] $end
$var parameter 8 * customId $end
$var reg 32 + counter0 [31:0] $end
$var reg 32 , counter1 [31:0] $end
$var reg 32 - counter2 [31:0] $end
$var reg 32 . counter3 [31:0] $end
$var reg 32 / result [31:0] $end
$upscope $end
$upscope $end
$enddefinitions $end
$comment Show the parameter values. $end
$dumpall
b1000 *
$end
#0
$dumpvars
b0 /
b0 .
b0 -
b0 ,
b0 +
bx000011100001 )
bx00 (
1'
x&
1%
0$
0#
b10001 "
x!
$end
#5
1#
#10
0#
#15
1#
#20
0%
0#
#25
b1 +
1#
#30
0#
#35
b10 +
1#
#40
0#
#45
b11 +
1#
#50
0#
#55
b100 +
1#
#60
0#
#65
b101 +
1#
#70
0#
#75
b110 +
1#
#80
0#
#85
b111 +
1#
#90
0#
#95
b1000 +
1#
#100
0#
#105
b1001 +
1#
#110
0#
#115
b1010 +
1#
#120
b1010 /
1$
b1000 "
0#
#125
b1011 /
b1011 +
1#
#130
0#
#135
b1100 /
b1100 +
1#
#140
0#
#145
b1101 /
b1101 +
1#
#150
0#
#155
b1110 /
b1110 +
1#
#160
0#
#165
b1111 /
b1111 +
1#
#170
0#
#175
b10000 /
b10000 +
1#
#180
0#
#185
b10001 /
b10001 +
1#
#190
0#
#195
b10010 /
b10010 +
1#
#200
0#
#205
b10011 /
b10011 +
1#
#210
0#
#215
b10100 /
b10100 +
1#
#220
b0 /
0$
bx111111111111 )
b10001 "
0#
#225
b0 +
1#
#230
0#
#235
1#
#240
1$
1&
bx000011000011 )
bx01 (
b1000 "
0#
#245
b1 /
b1 ,
b1 +
1#
#250
0#
#255
b10 /
b10 ,
b10 +
1#
#260
0#
#265
b11 /
b11 ,
b11 +
1#
#270
0#
#275
b100 /
b100 ,
b100 +
1#
#280
0#
#285
b101 /
b101 ,
b101 +
1#
#290
1!
bx000110000111 )
bx00 (
0#
#295
b0 /
b1 -
b110 ,
b0 +
1#
#300
0#
#305
b10 -
b111 ,
1#
#310
0#
#315
b11 -
b1000 ,
1#
#320
0#
#325
b100 -
b1001 ,
1#
#330
0#
#335
b101 -
b1010 ,
1#
